{"answers": [6, 3, 5, 13, 15, 9, 1, 11, 14, 8, 4, 7, 0, 2, 10, 12, 1, 15, 14, 11, 3, 2, 7, 13, 0, 9, 10, 12, 4, 8, 6, 5, 8, 1, 11, 14, 2, 4, 6, 15, 3, 13, 7, 10, 9, 0, 12, 5, 2, 0, 5, 10, 9, 3, 12, 1, 6, 14, 11, 4, 8, 13, 15, 7, 2, 9, 8, 4, 14, 0, 10, 12, 6, 5, 11, 15, 3, 1, 7, 13, 7, 0, 12, 10, 6, 5, 8, 4, 3, 13, 2, 1, 9, 14, 15, 11], "clues": [4, 5, 7, 9, 10, 12, 13, 16, 18, 20, 30, 31, 35, 37, 39, 41, 42, 45, 46, 49, 50, 51, 56, 57, 60, 67, 73, 76, 77, 80, 84, 86, 89, 92, 93, 94], "moves": [{"cell": 8, "group": 12, "onlyPlaceFor": 14}, {"cell": 68, "group": 1, "onlyPlaceFor": 14}, {"cell": 24, "group": 7, "onlyPlaceFor": 0}, {"cell": 59, "group": 10, "onlyPlaceFor": 4}, {"cell": 75, "group": 8, "onlyPlaceFor": 15}, {"cell": 6, "group": 12, "onlyPlaceFor": 1}, {"cell": 28, "group": 13, "onlyPlaceFor": 4}, {"cell": 17, "group": 0, "onlyPlaceFor": 15}, {"cell": 62, "group": 5, "onlyPlaceFor": 15}, {"cell": 87, "group": 17, "onlyPlaceFor": 4}, {"cell": 85, "group": 1, "onlyPlaceFor": 5}, {"cell": 47, "group": 11, "onlyPlaceFor": 5}, {"cell": 2, "group": 0, "onlyPlaceFor": 5}, {"cell": 0, "group": 12, "onlyPlaceFor": 6}, {"cell": 38, "group": 6, "onlyPlaceFor": 6}, {"cell": 1, "group": 12, "onlyPlaceFor": 3}, {"cell": 72, "group": 16, "onlyPlaceFor": 6}, {"cell": 43, "group": 14, "onlyPlaceFor": 10}, {"cell": 14, "group": 12, "onlyPlaceFor": 10}, {"cell": 95, "canOnlyBe": 11}, {"cell": 52, "group": 7, "onlyPlaceFor": 9}, {"cell": 25, "group": 6, "onlyPlaceFor": 9}, {"cell": 63, "group": 11, "onlyPlaceFor": 7}, {"cell": 48, "group": 7, "onlyPlaceFor": 2}, {"cell": 61, "canOnlyBe": 13}, {"cell": 29, "canOnlyBe": 8}, {"cell": 21, "canOnlyBe": 2}, {"cell": 66, "group": 16, "onlyPlaceFor": 8}, {"cell": 32, "group": 8, "onlyPlaceFor": 8}, {"group": 5, "numbers": [10, 7], "antiNumbers": [1, 11, 12], "couldBe": [26, 22], "couldNotBe": [58, 54, 33]}, {"group": 1, "numbers": [10, 7], "antiNumbers": [0, 12, 13], "couldBe": [70, 22], "couldNotBe": [69, 71, 23]}, {"cell": 69, "group": 1, "onlyPlaceFor": 0}, {"cell": 81, "group": 9, "onlyPlaceFor": 0}, {"group": 8, "numbers": [11, 1, 3], "antiNumbers": [12, 13], "couldBe": [88, 33, 34], "couldNotBe": [79, 71]}, {"group": 4, "numbers": [1, 2, 3, 9], "antiNumbers": [11, 12, 13], "couldBe": [44, 55, 40, 36], "couldNotBe": [27, 19, 23]}, {"group": 16, "numbers": [9, 2, 11], "antiNumbers": [7, 10, 12, 13], "couldBe": [64, 65, 74], "couldNotBe": [78, 70, 79, 71]}, {"cell": 70, "group": 16, "onlyPlaceFor": 10}, {"cell": 22, "canOnlyBe": 7}, {"cell": 26, "canOnlyBe": 10}, {"cell": 83, "group": 0, "onlyPlaceFor": 10}, {"cell": 78, "group": 16, "onlyPlaceFor": 7}, {"cell": 11, "group": 2, "onlyPlaceFor": 7}, {"cell": 54, "group": 9, "onlyPlaceFor": 12}, {"cell": 58, "canOnlyBe": 11}, {"cell": 53, "canOnlyBe": 3}, {"cell": 33, "canOnlyBe": 1}, {"cell": 55, "canOnlyBe": 1}, {"cell": 36, "canOnlyBe": 2}, {"cell": 34, "canOnlyBe": 11}, {"cell": 44, "canOnlyBe": 9}, {"cell": 88, "canOnlyBe": 3}, {"cell": 40, "canOnlyBe": 3}, {"cell": 74, "canOnlyBe": 11}, {"cell": 64, "canOnlyBe": 2}, {"cell": 27, "canOnlyBe": 12}, {"cell": 65, "canOnlyBe": 9}, {"cell": 82, "canOnlyBe": 12}, {"cell": 91, "canOnlyBe": 1}, {"cell": 23, "canOnlyBe": 13}, {"cell": 90, "canOnlyBe": 2}, {"cell": 3, "canOnlyBe": 13}, {"cell": 19, "canOnlyBe": 11}, {"cell": 71, "canOnlyBe": 12}, {"cell": 15, "canOnlyBe": 12}, {"cell": 79, "canOnlyBe": 13}], "difficulty": 500}