{"answers": [0, 10, 1, 15, 5, 7, 11, 9, 12, 4, 6, 14, 8, 13, 3, 2, 12, 8, 3, 11, 1, 15, 6, 10, 7, 2, 0, 13, 4, 5, 9, 14, 3, 5, 13, 0, 4, 1, 9, 11, 15, 2, 7, 8, 6, 14, 12, 10, 6, 10, 12, 7, 5, 0, 8, 2, 13, 14, 11, 9, 3, 4, 15, 1, 13, 6, 14, 9, 8, 4, 3, 2, 5, 1, 10, 11, 7, 0, 12, 15, 4, 7, 5, 2, 14, 13, 12, 0, 8, 15, 3, 9, 1, 6, 10, 11], "clues": [2, 4, 6, 10, 13, 17, 18, 22, 24, 29, 30, 35, 36, 37, 40, 41, 43, 47, 50, 51, 55, 58, 60, 67, 68, 70, 71, 78, 80, 85, 87, 91, 92, 94, 95], "moves": [{"cell": 7, "group": 12, "onlyPlaceFor": 9}, {"cell": 59, "group": 4, "onlyPlaceFor": 9}, {"cell": 83, "group": 17, "onlyPlaceFor": 2}, {"cell": 38, "group": 9, "onlyPlaceFor": 9}, {"cell": 88, "group": 8, "onlyPlaceFor": 8}, {"cell": 12, "group": 12, "onlyPlaceFor": 8}, {"cell": 54, "group": 15, "onlyPlaceFor": 8}, {"cell": 90, "group": 17, "onlyPlaceFor": 3}, {"cell": 14, "group": 12, "onlyPlaceFor": 3}, {"cell": 32, "group": 4, "onlyPlaceFor": 3}, {"cell": 25, "group": 6, "onlyPlaceFor": 2}, {"cell": 39, "group": 14, "onlyPlaceFor": 11}, {"cell": 75, "group": 8, "onlyPlaceFor": 11}, {"cell": 19, "group": 4, "onlyPlaceFor": 11}, {"cell": 15, "group": 3, "onlyPlaceFor": 2}, {"cell": 44, "group": 14, "onlyPlaceFor": 6}, {"cell": 49, "group": 8, "onlyPlaceFor": 10}, {"cell": 46, "group": 11, "onlyPlaceFor": 12}, {"cell": 42, "group": 6, "onlyPlaceFor": 7}, {"cell": 34, "group": 14, "onlyPlaceFor": 13}, {"cell": 5, "group": 1, "onlyPlaceFor": 7}, {"cell": 23, "group": 1, "onlyPlaceFor": 10}, {"group": 15, "numbers": [1, 13], "antiNumbers": [0, 4, 5, 6, 14, 15], "couldBe": [56, 63], "couldNotBe": [48, 62, 57, 53, 61, 52]}, {"group": 5, "numbers": [0, 10, 4, 15], "antiNumbers": [5, 14], "couldBe": [26, 9, 62, 1], "couldNotBe": [33, 45]}, {"group": 13, "numbers": [1, 12, 13], "antiNumbers": [0, 4, 14, 15], "couldBe": [16, 20, 27], "couldNotBe": [21, 28, 26, 31]}, {"group": 4, "numbers": [1, 13], "antiNumbers": [0, 12, 14], "couldBe": [27, 63], "couldNotBe": [0, 31, 8]}, {"group": 15, "numbers": [5, 6], "antiNumbers": [0, 4, 14, 15], "couldBe": [48, 52], "couldNotBe": [61, 53, 62, 57]}, {"group": 7, "numbers": [4, 14, 15], "antiNumbers": [1, 12, 13], "couldBe": [11, 3, 28], "couldNotBe": [56, 16, 20]}, {"cell": 8, "group": 2, "onlyPlaceFor": 12}, {"pointingGroup": 17, "pointingValue": 7, "pointingIntoGroup": 9, "pointingCells": [81, 93], "affectedCells": [66]}, {"pointingGroup": 15, "pointingValue": 14, "pointingIntoGroup": 6, "pointingCells": [57, 53, 61], "affectedCells": [21]}, {"pointingGroup": 12, "pointingValue": 4, "pointingIntoGroup": 2, "pointingCells": [11, 9], "affectedCells": [73, 72, 26]}, {"pointingGroup": 13, "pointingValue": 14, "pointingIntoGroup": 3, "pointingCells": [31, 28], "affectedCells": [93, 79, 76, 77]}, {"group": 16, "chain": [72, 63, 56, 20, 69], "value": 1, "ruledOutFrom": [72, 69], "parity": "odd"}, {"cell": 73, "group": 16, "onlyPlaceFor": 1}, {"cell": 27, "canOnlyBe": 13}, {"cell": 56, "canOnlyBe": 13}, {"cell": 16, "canOnlyBe": 12}, {"cell": 63, "canOnlyBe": 1}, {"cell": 20, "canOnlyBe": 1}, {"cell": 64, "group": 16, "onlyPlaceFor": 13}, {"cell": 86, "group": 10, "onlyPlaceFor": 12}, {"cell": 76, "group": 16, "onlyPlaceFor": 7}, {"cell": 81, "group": 0, "onlyPlaceFor": 7}, {"group": 3, "numbers": [0, 4, 14], "antiNumbers": [6, 15], "couldBe": [28, 77, 31], "couldNotBe": [79, 93]}, {"group": 10, "numbers": [5, 6], "antiNumbers": [0, 4, 14], "couldBe": [65, 82], "couldNotBe": [77, 57, 69]}, {"group": 0, "numbers": [0, 10, 14, 15], "antiNumbers": [5, 6], "couldBe": [0, 66, 3, 1], "couldNotBe": [82, 65]}, {"pointingGroup": 16, "pointingValue": 4, "pointingIntoGroup": 10, "pointingCells": [77, 69], "affectedCells": [57]}, {"pointingGroup": 7, "pointingValue": 15, "pointingIntoGroup": 12, "pointingCells": [11, 3], "affectedCells": [1, 9]}, {"group": 17, "chain": [93, 79, 84], "value": 15, "ruledOutFrom": [93, 84], "parity": "odd"}, {"cell": 93, "canOnlyBe": 6}, {"cell": 84, "canOnlyBe": 14}, {"cell": 82, "canOnlyBe": 5}, {"cell": 79, "canOnlyBe": 15}, {"cell": 52, "canOnlyBe": 5}, {"cell": 89, "canOnlyBe": 15}, {"cell": 69, "canOnlyBe": 4}, {"cell": 33, "canOnlyBe": 5}, {"cell": 65, "canOnlyBe": 6}, {"cell": 48, "canOnlyBe": 6}, {"cell": 26, "canOnlyBe": 0}, {"cell": 77, "canOnlyBe": 0}, {"cell": 21, "canOnlyBe": 15}, {"cell": 45, "canOnlyBe": 14}, {"cell": 31, "canOnlyBe": 14}, {"cell": 1, "canOnlyBe": 10}, {"cell": 66, "canOnlyBe": 14}, {"cell": 57, "canOnlyBe": 14}, {"cell": 61, "canOnlyBe": 4}, {"cell": 72, "canOnlyBe": 5}, {"cell": 28, "canOnlyBe": 4}, {"cell": 0, "canOnlyBe": 0}, {"cell": 9, "canOnlyBe": 4}, {"cell": 74, "canOnlyBe": 10}, {"cell": 3, "canOnlyBe": 15}, {"cell": 53, "canOnlyBe": 0}, {"cell": 62, "canOnlyBe": 15}, {"cell": 11, "canOnlyBe": 14}], "difficulty": 700}