{"answers": [2, 0, 10, 7, 13, 4, 8, 3, 14, 9, 15, 5, 11, 6, 12, 1, 8, 5, 1, 9, 10, 0, 7, 12, 11, 4, 3, 6, 13, 2, 14, 15, 4, 5, 1, 15, 0, 8, 11, 6, 7, 13, 14, 9, 10, 2, 3, 12, 0, 7, 12, 8, 2, 9, 10, 3, 4, 6, 11, 1, 14, 13, 15, 5, 6, 15, 12, 13, 9, 5, 14, 11, 0, 8, 1, 2, 4, 10, 7, 3, 14, 4, 3, 11, 6, 15, 2, 1, 10, 13, 12, 7, 9, 5, 0, 8], "clues": [1, 4, 8, 9, 11, 12, 15, 16, 17, 20, 22, 27, 28, 29, 32, 36, 37, 42, 43, 44, 45, 47, 48, 55, 56, 58, 59, 61, 66, 69, 84, 85, 87, 95], "moves": [{"cell": 51, "group": 4, "onlyPlaceFor": 8}, {"cell": 6, "group": 1, "onlyPlaceFor": 8}, {"cell": 73, "group": 2, "onlyPlaceFor": 8}, {"cell": 33, "group": 14, "onlyPlaceFor": 5}, {"cell": 52, "group": 15, "onlyPlaceFor": 2}, {"cell": 7, "canOnlyBe": 3}, {"cell": 0, "group": 4, "onlyPlaceFor": 2}, {"cell": 41, "group": 14, "onlyPlaceFor": 13}, {"cell": 93, "group": 17, "onlyPlaceFor": 5}, {"cell": 63, "group": 11, "onlyPlaceFor": 5}, {"cell": 60, "group": 7, "onlyPlaceFor": 14}, {"cell": 40, "group": 4, "onlyPlaceFor": 7}, {"cell": 3, "group": 7, "onlyPlaceFor": 7}, {"cell": 39, "group": 7, "onlyPlaceFor": 6}, {"cell": 54, "canOnlyBe": 10}, {"group": 13, "numbers": [0, 1, 3, 4, 14], "antiNumbers": [9, 11, 12, 15], "couldBe": [26, 21, 18, 25, 30], "couldNotBe": [19, 24, 31, 23]}, {"cell": 24, "group": 13, "onlyPlaceFor": 11}, {"cell": 35, "canOnlyBe": 15}, {"cell": 50, "canOnlyBe": 12}, {"cell": 5, "canOnlyBe": 4}, {"cell": 21, "canOnlyBe": 0}, {"cell": 25, "group": 13, "onlyPlaceFor": 4}, {"group": 17, "numbers": [9, 11, 4, 14], "antiNumbers": [0, 2, 3, 7, 10, 12, 13], "couldBe": [80, 92, 81, 83], "couldNotBe": [89, 90, 88, 82, 86, 94, 91]}, {"cell": 67, "group": 0, "onlyPlaceFor": 13}, {"cell": 89, "group": 9, "onlyPlaceFor": 13}, {"cell": 18, "group": 0, "onlyPlaceFor": 1}, {"cell": 26, "canOnlyBe": 3}, {"cell": 30, "canOnlyBe": 14}, {"cell": 92, "canOnlyBe": 9}, {"cell": 49, "canOnlyBe": 7}, {"cell": 53, "canOnlyBe": 9}, {"cell": 91, "group": 17, "onlyPlaceFor": 7}, {"cell": 74, "canOnlyBe": 1}, {"cell": 38, "canOnlyBe": 11}, {"cell": 46, "canOnlyBe": 3}, {"cell": 70, "canOnlyBe": 14}, {"cell": 81, "canOnlyBe": 4}, {"cell": 34, "canOnlyBe": 1}, {"cell": 83, "canOnlyBe": 11}, {"cell": 78, "canOnlyBe": 7}, {"cell": 80, "canOnlyBe": 14}, {"cell": 68, "canOnlyBe": 9}, {"cell": 23, "canOnlyBe": 12}, {"cell": 31, "canOnlyBe": 15}, {"cell": 86, "canOnlyBe": 2}, {"cell": 19, "canOnlyBe": 9}, {"cell": 13, "canOnlyBe": 6}, {"cell": 88, "canOnlyBe": 10}, {"cell": 71, "canOnlyBe": 11}, {"cell": 62, "canOnlyBe": 15}, {"cell": 82, "canOnlyBe": 3}, {"cell": 75, "canOnlyBe": 2}, {"cell": 79, "canOnlyBe": 3}, {"cell": 57, "canOnlyBe": 6}, {"cell": 64, "canOnlyBe": 6}, {"cell": 72, "canOnlyBe": 0}, {"cell": 77, "canOnlyBe": 10}, {"cell": 76, "canOnlyBe": 4}, {"cell": 90, "canOnlyBe": 12}, {"cell": 65, "canOnlyBe": 15}, {"cell": 14, "canOnlyBe": 12}, {"cell": 94, "canOnlyBe": 0}, {"cell": 10, "canOnlyBe": 15}, {"cell": 2, "canOnlyBe": 10}], "difficulty": 500}