{"answers": [9, 4, 11, 12, 7, 2, 6, 14, 5, 10, 8, 3, 13, 15, 0, 1, 0, 3, 5, 6, 15, 12, 1, 4, 9, 14, 13, 11, 10, 7, 8, 2, 3, 14, 10, 13, 15, 6, 1, 7, 12, 11, 5, 2, 0, 9, 4, 8, 4, 15, 12, 1, 11, 9, 0, 14, 6, 13, 3, 8, 5, 2, 7, 10, 13, 1, 2, 7, 11, 10, 8, 5, 15, 0, 4, 6, 12, 14, 3, 9, 8, 10, 15, 14, 0, 13, 9, 3, 2, 12, 7, 1, 11, 5, 4, 6], "clues": [0, 1, 4, 9, 11, 17, 20, 23, 25, 31, 35, 37, 38, 39, 40, 42, 44, 45, 46, 49, 50, 54, 55, 57, 61, 64, 66, 75, 77, 80, 81, 84, 86, 91, 92], "moves": [{"cell": 34, "canOnlyBe": 10}, {"cell": 32, "canOnlyBe": 3}, {"cell": 28, "group": 13, "onlyPlaceFor": 10}, {"cell": 29, "group": 6, "onlyPlaceFor": 7}, {"cell": 33, "group": 8, "onlyPlaceFor": 14}, {"cell": 24, "group": 13, "onlyPlaceFor": 9}, {"cell": 53, "group": 6, "onlyPlaceFor": 9}, {"cell": 88, "group": 8, "onlyPlaceFor": 2}, {"cell": 16, "group": 13, "onlyPlaceFor": 0}, {"cell": 73, "group": 16, "onlyPlaceFor": 0}, {"cell": 14, "group": 3, "onlyPlaceFor": 0}, {"cell": 67, "group": 8, "onlyPlaceFor": 7}, {"cell": 21, "group": 13, "onlyPlaceFor": 12}, {"cell": 90, "group": 2, "onlyPlaceFor": 7}, {"cell": 79, "group": 3, "onlyPlaceFor": 9}, {"cell": 62, "group": 11, "onlyPlaceFor": 7}, {"cell": 19, "group": 13, "onlyPlaceFor": 6}, {"cell": 2, "canOnlyBe": 11}, {"cell": 82, "canOnlyBe": 15}, {"cell": 10, "canOnlyBe": 8}, {"cell": 6, "canOnlyBe": 6}, {"cell": 65, "canOnlyBe": 1}, {"cell": 71, "canOnlyBe": 5}, {"cell": 18, "canOnlyBe": 5}, {"cell": 51, "canOnlyBe": 1}, {"cell": 48, "canOnlyBe": 4}, {"cell": 36, "group": 14, "onlyPlaceFor": 15}, {"cell": 72, "group": 2, "onlyPlaceFor": 15}, {"cell": 13, "group": 12, "onlyPlaceFor": 15}, {"cell": 94, "group": 10, "onlyPlaceFor": 4}, {"cell": 58, "group": 15, "onlyPlaceFor": 3}, {"cell": 74, "group": 9, "onlyPlaceFor": 4}, {"cell": 95, "group": 17, "onlyPlaceFor": 6}, {"cell": 56, "group": 15, "onlyPlaceFor": 6}, {"cell": 89, "group": 2, "onlyPlaceFor": 12}, {"cell": 83, "canOnlyBe": 14}, {"cell": 87, "canOnlyBe": 3}, {"cell": 3, "canOnlyBe": 12}, {"cell": 85, "canOnlyBe": 13}, {"cell": 93, "canOnlyBe": 5}, {"cell": 15, "canOnlyBe": 1}, {"cell": 5, "canOnlyBe": 2}, {"cell": 12, "canOnlyBe": 13}, {"cell": 7, "canOnlyBe": 14}, {"cell": 30, "canOnlyBe": 8}, {"cell": 41, "canOnlyBe": 11}, {"cell": 8, "canOnlyBe": 5}, {"cell": 27, "canOnlyBe": 11}, {"cell": 22, "canOnlyBe": 1}, {"cell": 76, "canOnlyBe": 12}, {"cell": 78, "canOnlyBe": 3}, {"cell": 47, "canOnlyBe": 8}, {"cell": 26, "canOnlyBe": 13}, {"cell": 63, "canOnlyBe": 10}, {"cell": 43, "canOnlyBe": 2}, {"cell": 68, "canOnlyBe": 11}, {"cell": 60, "canOnlyBe": 5}, {"cell": 52, "canOnlyBe": 11}, {"cell": 59, "canOnlyBe": 8}, {"cell": 70, "canOnlyBe": 8}, {"cell": 69, "canOnlyBe": 10}], "difficulty": 200}